somali_abbreviation/__init__.py
somali_abbreviation/abbreviation.py
somali_abbreviation/data/abbreviation_dict.json
somali_abbreviation-0.1.0.dist-info/METADATA
somali_abbreviation-0.1.0.dist-info/WHEEL
somali_abbreviation-0.1.0.dist-info/top_level.txt
somali_abbreviation-0.1.0.dist-info/RECORD
