Metadata-Version: 2.4
Name: somali_abbreviation
Version: 0.1.0
Summary: A Somali abbreviation replacement library
Home-page: https://github.com/abdoltd/somali_abbreviation
Author: ABDOL
Author-email: abdoldevtra@example.com
Dynamic: author
Dynamic: author-email
Dynamic: description-content-type
Dynamic: home-page
Dynamic: summary
